{
  "rulesDirectory": ["tslint-plugin-prettier"],
  "extends": ["tslint:latest", "tslint-react", "tslint-config-prettier"],
  "rules": {
    "prettier": true,
    "jsx-no-multiligne-js": false,
    "jsx-no-lambda": false,
    "import-name": false,
    "no-boolean-literal-compare": false,
    "no-implicit-dependencies": [true, "dev"],
    "no-submodule-imports": [true, "lodash"],
    "object-literal-sort-keys": false,
    "interface-name": false,
    "member-access": [true, "no-public"],
    "ordered-imports": false
  },
  "jsRules": {
    "object-literal-sort-keys": false
  },
  "linterOptions": {
    "exclude": ["public/**/*"]
  }
}
